cloudspeak/__init__.py
cloudspeak/api/__init__.py
cloudspeak/api/azure/__init__.py
cloudspeak/api/azure/container.py
cloudspeak/api/azure/file.py
cloudspeak/api/azure/service.py
cloudspeak/api/azure/leases/__init__.py
cloudspeak/api/azure/leases/leases_handler.py
cloudspeak/api/azure/progress/__init__.py
cloudspeak/api/azure/progress/progress_multiple.py
cloudspeak/api/azure/progress/progress_single.py
cloudspeak/api/azure/snapshots/__init__.py
cloudspeak/api/azure/snapshots/snapshots.py
cloudspeak/api/interface/__init__.py
cloudspeak/api/interface/container.py
cloudspeak/api/interface/file.py
cloudspeak/api/interface/service.py
cloudspeak/azure/__init__.py
cloudspeak/azure/credentials.py
cloudspeak/azure/factory.py
cloudspeak/azure/remote_dict.py
cloudspeak/config/__init__.py
cloudspeak/serializers/__init__.py
cloudspeak/serializers/serializer_joblib.py
cloudspeak/storage/__init__.py
cloudspeak/storage/azure/__init__.py
cloudspeak/storage/azure/container.py
cloudspeak/storage/azure/file.py
cloudspeak/storage/azure/service.py
cloudspeak/storage/azure/blob/__init__.py
cloudspeak/storage/azure/blob/container.py
cloudspeak/storage/azure/blob/file.py
cloudspeak/storage/azure/blob/leases/__init__.py
cloudspeak/storage/azure/blob/leases/leases_handler.py
cloudspeak/storage/azure/blob/progress/__init__.py
cloudspeak/storage/azure/blob/progress/progress_multiple.py
cloudspeak/storage/azure/blob/progress/progress_single.py
cloudspeak/storage/azure/blob/snapshots/__init__.py
cloudspeak/storage/azure/blob/snapshots/snapshots.py
cloudspeak/storage/azure/leases/__init__.py
cloudspeak/storage/azure/leases/leases_handler.py
cloudspeak/storage/azure/progress/__init__.py
cloudspeak/storage/azure/progress/progress_multiple.py
cloudspeak/storage/azure/progress/progress_single.py
cloudspeak/storage/azure/queue/__init__.py
cloudspeak/storage/azure/queue/message.py
cloudspeak/storage/azure/queue/queue.py
cloudspeak/storage/azure/queue/updates/__init__.py
cloudspeak-0.1.2.dist-info/METADATA
cloudspeak-0.1.2.dist-info/WHEEL
cloudspeak-0.1.2.dist-info/top_level.txt
cloudspeak-0.1.2.dist-info/RECORD
