Metadata-Version: 2.1
Name: cloudspeak
Version: 0.1.2
Summary: Set of python tools that eases integration of cloud services in Python projects
Home-page: https://github.com/mlhost/cloudspeak
Keywords: python,cloud,remote,dict,abstraction,azure,storage,blob
Requires-Dist: tqdm (==4.64.1)
Requires-Dist: joblib (==1.2.0)
Requires-Dist: azure-storage-blob (==12.14.1)
Requires-Dist: azure-storage-queue (==12.3.0)
Requires-Dist: pandas (==1.5.2)
Requires-Dist: lz4 (==4.0.0)
